{
"qjjxdrvlmaep4agzpncehb7w":["channelone.systems","hrln "],
"b3bymlekncs2awmy3xuzl2zt":"dan-hrl",
"fuug5aj2ikqqvbg5pljhg7f3":"hrlomax",
"e2yfxnuybhfj6pzbzsttxmkc":["hrl","Harel"],
"lns4npkfyihfe7xt4x6tyvru":["hrlshnv","hrlshnv"],
"3qg4akgziquzmpqyvcxzitlt":"hrly",
"l5nylsf4vx463cgazsyrw4vn":"hrlot",
"zpirg3f7fzn4hionkfgrlsik":["hrld","Harry"],
"qgrw4iegvhhcqgszoca5anf3":["hrleon","Leon "],
"jiqvk3dyj4j32hdkjwugofy5":"hrlatinam",
"g624dixdi26wvety6uht6xd3":"hrlemgo",
"kavpbongm7fjbvkibdl5oalr":"hrllll",
"qnlpzsk27hmvyqrilucafqmp":["hrldcgn","Schaelsickpics"],
"lrxasjokkp3ojyfabq6p2ufj":["kampfmopsi","Kampfmops 😇 Wild & Gefährlich 🤭"],
"5l5knnlyzcqlciuvkq64adu3":["luishrl","Luis_HRL"],
"afjzh4s632a6q4cqwnlizpfp":["michaelhk00","Geheimgefährlicher"],
"kkcfnswsrc4ammgmdx7dt6yh":["queenofchaos","Queen of Chaos (Flockenstieliger Hexenröhrling 👻)"],
"wmasvqu24kgknfuawnuyugsy":["rolfpoeler","Gefährliches Weinwissen"],
"nh4lwar67a2ys7yffonbvgmz":["sergejfaehrlich","Sergej Fährlich"],
"4oq2tduowf4lroq3sze6hjoq":["stvnhrlnd","🍩 Stvn Hrlnd (He/Him)"],
"jbla2kwdsuf4aeirpukq3dqu":["txw56","Gefährliches Halbwissen"],
"unoiplfnrkr5mzxd3cfyqzui":["wbcenobyte","Sergej Fährlich"],
"o7cn3jsxle5bjv4q3uwjj5od":["wuehrlinho","Ben Wührl "]
}
