{
"iujb7q577sardpvc46we2pah":["hfayefaye","Faye"],
"nthvqw3linz2parhzlincn7n":["hfarahani","Hossein"],
"554cgok5zlrn7vb6m4r2kwnl":"hfa",
"lflt27iuj5v5seozqjvxt2g4":["hfagundes","Fagundes (:"],
"5efnvkrp5kn5en2qfigii3v6":["hfarash","Hinoa F. Arash"],
"tmcarae7x4ket4rket6dnzvd":"hfallah",
"ueixt7eikksh37hxcnccs5na":["hfayet","Héloïse Fayet"],
"t7zakygaprqlqmj6wgur6ei5":["hfahmy","Hossam Fahmy"],
"cdopi3vzzlchexolfxditasu":["hfarruda","Henrique F. de Arruda"],
"3xjljzjapm6mw5mpudqp2uo4":"hface",
"shbyhtnjmu2jn4b5uwjmngbc":"hfaria",
"cyz6lvmyzrfhfa3ewvkh2fuu":["hfalicia","Heart Forth, Alicia"],
"wzssvxn7cugjgeslm5cogciv":["hfazelinia","Hossein Fazelinia"],
"odtmhh6bn2dvaszhr4bwkgtt":["hfailslife","James (Shayera’s Version)"],
"f76tkhm3zwmnml47tmlxtycm":"hfaceless",
"c6pcgx3ho5s67hyj73y2zpo4":"hfanatnyit",
"xxihtoiu7rmv5vywixdf23h7":"hface77",
"5wohzpnfc5eu5cjeqyqffqwg":["hfaye","faye"],
"eg7dljx2mhnfjkqm6a2hwk5k":"hfalbk",
"iwhbnlajh27jsvcwqlk4a433":["hfalet","Hervé Falet"],
"nnyrtyht3csnlybylioybt7j":["hfabritius","Henna Fabritius"],
"nv575aefcv5qsmwweciqwhfe":"hfav"
}
